dexscreener/__init__.py
dexscreener/client.py
dexscreener/guard_util.py
dexscreener/http_client.py
dexscreener/models.py
dexscreener/ratelimit.py
dexscreener-1.3.dist-info/licenses/LICENSE
dexscreener-1.3.dist-info/METADATA
dexscreener-1.3.dist-info/WHEEL
dexscreener-1.3.dist-info/top_level.txt
dexscreener-1.3.dist-info/RECORD
