Metadata-Version: 2.4
Name: dexscreener
Version: 1.3
Summary: Python wrapper for the 'dexscreener.com' API
Home-page: https://github.com/nixonjoshua98/dexscreener
Download-URL: https://github.com/nixonjoshua98/dexscreener/releases
Author: Joshua Nixon
Author-email: nixonjoshua98@gmail.com
License: MIT
Keywords: dexscreener,crypto,cryptocurrency,bitcoin
Classifier: Programming Language :: Python :: 3
Classifier: License :: OSI Approved :: MIT License
Classifier: Operating System :: OS Independent
Classifier: Development Status :: 5 - Production/Stable
Classifier: Intended Audience :: Developers
Classifier: Topic :: Software Development :: Build Tools
Requires-Python: >=3.9
License-File: LICENSE
Requires-Dist: requests
Requires-Dist: pydantic
Requires-Dist: certifi
Requires-Dist: aiohttp
Dynamic: author
Dynamic: author-email
Dynamic: classifier
Dynamic: description
Dynamic: description-content-type
Dynamic: download-url
Dynamic: home-page
Dynamic: keywords
Dynamic: license
Dynamic: license-file
Dynamic: requires-dist
Dynamic: requires-python
Dynamic: summary
